LICENSE
MANIFEST.in
README.rst
changelog.rst
setup.py
Flask_DB2.egg-info/PKG-INFO
Flask_DB2.egg-info/SOURCES.txt
Flask_DB2.egg-info/dependency_links.txt
Flask_DB2.egg-info/not-zip-safe
Flask_DB2.egg-info/requires.txt
Flask_DB2.egg-info/top_level.txt
flask_db2/.base.py.swp
flask_db2/.errors.py.swp
flask_db2/__init__.py
flask_db2/base.py
flask_db2/errors.py
flask_db2/__pycache__/__init__.cpython-34.pyc
flask_db2/__pycache__/base.cpython-34.pyc